WayKey/__init__.py
WayKey/library/commands.py
waykey-0.1.0.dist-info/WHEEL
waykey-0.1.0.dist-info/METADATA
waykey-0.1.0.dist-info/RECORD
